{
	"info": {
		"_postman_id": "bf1e9aff-da45-4793-bd9b-148e1a3dd49d",
		"name": "New Collection",
		"schema": "https://schema.getpostman.com/json/collection/v2.1.0/collection.json"
	},
	"item": [
		{
			"name": "GetEndereço",
			"request": {
				"method": "GET",
				"header": [],
				"url": {
					"raw": "http://localhost:8080/api/enderecos",
					"protocol": "http",
					"host": [
						"localhost"
					],
					"port": "8080",
					"path": [
						"api",
						"enderecos"
					]
				}
			},
			"response": []
		},
		{
			"name": "PostEndereco",
			"request": {
				"method": "POST",
				"header": [],
				"body": {
					"mode": "raw",
					"raw": " {\r\n        \"id\": 2,\r\n        \"cep\": \"123123\",\r\n        \"logradouro\": \"3123123\",\r\n        \"numero\": \"312312\",\r\n        \"complemento\": \"3123123\",\r\n        \"idPessoa\": 1\r\n    }",
					"options": {
						"raw": {
							"language": "json"
						}
					}
				},
				"url": {
					"raw": "http://localhost:8080/api/enderecos",
					"protocol": "http",
					"host": [
						"localhost"
					],
					"port": "8080",
					"path": [
						"api",
						"enderecos"
					]
				}
			},
			"response": []
		},
		{
			"name": "DeleteEndereco",
			"request": {
				"method": "DELETE",
				"header": [],
				"body": {
					"mode": "raw",
					"raw": "{\r\n        \"id\": 2,\r\n        \"cep\": \"123123\",\r\n        \"logradouro\": \"3123123\",\r\n        \"numero\": \"312312\",\r\n        \"complemento\": \"3123123\",\r\n        \"idPessoa\": 1\r\n    }",
					"options": {
						"raw": {
							"language": "json"
						}
					}
				},
				"url": {
					"raw": "http://localhost:8080/api/enderecos",
					"protocol": "http",
					"host": [
						"localhost"
					],
					"port": "8080",
					"path": [
						"api",
						"enderecos"
					]
				}
			},
			"response": []
		},
		{
			"name": "PutEndereco",
			"event": [
				{
					"listen": "test",
					"script": {
						"exec": [
							""
						],
						"type": "text/javascript"
					}
				}
			],
			"request": {
				"method": "PUT",
				"header": [],
				"body": {
					"mode": "raw",
					"raw": "{\r\n        \"id\": 2,\r\n        \"cep\": \"111\",\r\n        \"logradouro\": \"111111\",\r\n        \"numero\": \"11\",\r\n        \"complemento\": \"a\",\r\n        \"idPessoa\": 1\r\n    }",
					"options": {
						"raw": {
							"language": "json"
						}
					}
				},
				"url": {
					"raw": "http://localhost:8080/api/enderecos",
					"protocol": "http",
					"host": [
						"localhost"
					],
					"port": "8080",
					"path": [
						"api",
						"enderecos"
					]
				}
			},
			"response": []
		},
		{
			"name": "GetPessoas",
			"request": {
				"method": "GET",
				"header": [],
				"url": {
					"raw": "http://localhost:8080/api/pessoas",
					"protocol": "http",
					"host": [
						"localhost"
					],
					"port": "8080",
					"path": [
						"api",
						"pessoas"
					]
				}
			},
			"response": []
		},
		{
			"name": "PostPessoas",
			"request": {
				"method": "POST",
				"header": [],
				"body": {
					"mode": "raw",
					"raw": "\r\n{\r\n    \"id\": 2,\r\n    \"nome\": \"dsadsa\",\r\n    \"sobrenome\": \"ferronato\",\r\n    \"rg\": \"0000000\",\r\n    \"cpf\": \"99999999999\"\r\n}\r\n",
					"options": {
						"raw": {
							"language": "json"
						}
					}
				},
				"url": {
					"raw": "http://localhost:8080/api/pessoas",
					"protocol": "http",
					"host": [
						"localhost"
					],
					"port": "8080",
					"path": [
						"api",
						"pessoas"
					]
				}
			},
			"response": []
		},
		{
			"name": "DeletePessoas",
			"request": {
				"method": "DELETE",
				"header": [],
				"body": {
					"mode": "raw",
					"raw": "{\r\n    \"id\": 2,\r\n    \"nome\": \"dsadsa\",\r\n    \"sobrenome\": \"ferronato\",\r\n    \"rg\": \"0000000\",\r\n    \"cpf\": \"99999999999\"\r\n}",
					"options": {
						"raw": {
							"language": "json"
						}
					}
				},
				"url": {
					"raw": "http://localhost:8080/api/pessoas",
					"protocol": "http",
					"host": [
						"localhost"
					],
					"port": "8080",
					"path": [
						"api",
						"pessoas"
					]
				}
			},
			"response": []
		},
		{
			"name": "PutPessoas",
			"request": {
				"method": "PUT",
				"header": [],
				"body": {
					"mode": "raw",
					"raw": "{\r\n    \"id\": 1,\r\n    \"nome\": \"thiago\",\r\n    \"sobrenome\": \"ferronato\",\r\n    \"rg\": \"a\",\r\n    \"cpf\": \"a\"\r\n}",
					"options": {
						"raw": {
							"language": "json"
						}
					}
				},
				"url": {
					"raw": "http://localhost:8080/api/pessoas",
					"protocol": "http",
					"host": [
						"localhost"
					],
					"port": "8080",
					"path": [
						"api",
						"pessoas"
					]
				}
			},
			"response": []
		}
	]
}